README.rst
setup.cfg
setup.py
frhd/Decode.py
frhd/Encode.py
frhd/Loader.py
frhd/Track.py
frhd/__init__.py
frhd_python.egg-info/PKG-INFO
frhd_python.egg-info/SOURCES.txt
frhd_python.egg-info/dependency_links.txt
frhd_python.egg-info/requires.txt
frhd_python.egg-info/top_level.txt