Metadata-Version: 1.1
Name: frhd-python
Version: 4.8
Summary: Library to edit FRHD tracks
Home-page: https://github.com/gaetgu/frhd
Author: Gaetgu
Author-email: gabriel.ethan.phantom@gmail.com
License: MIT License
Download-URL: https://github.com/gaetgu/frhd/archive/v_4.8.tar.gz
Keywords: development freeriderhd freerider frhd code track tracks
Platform: UNKNOWN
Classifier: Development Status :: 2 - Pre-Alpha
Classifier: Intended Audience :: Developers
Classifier: Topic :: Software Development :: Code Generators
Classifier: License :: OSI Approved :: MIT License
Classifier: Programming Language :: Python :: 3 :: Only
